{
	"TagId": 0,
	"ThemeName": {
		"m_identifier": 1231049730
	},
	"EmblemShaderName": {
		"m_identifier": 0
	},
	"CommonData": {
		"Id": "013-001-b2e7c989",
		"HideUntilOwned": true,
		"Title": "Collaborative Process",
		"Description": "No roughhousing in the triage room!",
		"FeatureFlag": true,
		"ItemAvailability": "",
		"DateReleased": {
			"ISO8601Date": ""
		},
		"AltName": "013-001-b2e7c989",
		"IconStringId": {
			"m_identifier": -1
		},
		"SpriteBitmap": 0,
		"SpriteFrameIndex": 0,
		"AltSpriteBitmap": 0,
		"AltSpriteFrameIndex": 0,
		"DisplayPath": {
			"Width": 1030,
			"Height": 812,
			"Media": {
				"MediaUrl": {
					"AuthorityId": "",
					"Path": "progression/Inventory/Emblems/343unicorns_ducttapeunicorn.png",
					"RetryPolicyId": "",
					"TopicName": "",
					"AcknowledgementTypeId": "NoAcknowledgement",
					"AuthenticationLifetimeExtensionSupported": false,
					"ClearanceAware": false
				},
				"MimeType": "",
				"Caption": "",
				"AlternateText": "",
				"FolderPath": "",
				"FileName": ""
			},
			"MimeType": "image/png",
			"FolderPath": "progression/Inventory/Emblems",
			"FileName": "343unicorns_ducttapeunicorn.png"
		},
		"Quality": "Legendary",
		"ManufacturerId": 0,
		"Type": "ArmorEmblem",
		"RewardTrack": "",
		"ParentPaths": [
			{
				"Path": "Inventory/Armor/Themes/007-001-olympus-c13d0b38.json",
				"Type": "ArmorTheme"
			},
			{
				"Path": "Inventory/Armor/Themes/007-000-lone-wolf-0903655e.json",
				"Type": "ArmorTheme"
			},
			{
				"Path": "Inventory/Armor/Themes/007-000-eagle-strike-0903655e.json",
				"Type": "ArmorTheme"
			},
			{
				"Path": "Inventory/Armor/Themes/007-001-reach-2564121f.json",
				"Type": "ArmorTheme"
			},
			{
				"Path": "Inventory/Armor/Themes/007-001-samurai-55badb14.json",
				"Type": "ArmorTheme"
			}
		],
		"SortingMetadata": {
			"categoryWeight": 0,
			"subCategoryWeight": 0
		},
		"SeasonNumber": 2,
		"OriginalSeasonNumber": 2,
		"Season": {
			"status": "Test",
			"value": "Season 2",
			"translations": {}
		}
	},
	"AvailableConfigurations": [
		{
			"ConfigurationId": 726761566,
			"ConfigurationPath": "Configuration/Emblems/Coatings/1000-000-63563fd6.json"
		},
		{
			"ConfigurationId": 1337929658,
			"ConfigurationPath": "Configuration/Emblems/Coatings/1000-000-2bff0b6b.json"
		},
		{
			"ConfigurationId": 2002320468,
			"ConfigurationPath": "Configuration/Emblems/Coatings/1000-000-98ab86a6.json"
		},
		{
			"ConfigurationId": 717587286,
			"ConfigurationPath": "Configuration/Emblems/Coatings/1000-000-f9ca272b.json"
		}
	]
}